keccaky/__init__.py
keccaky/algorithm.py
keccaky/functions.py
keccaky-0.3.1.dist-info/LICENSE
keccaky-0.3.1.dist-info/METADATA
keccaky-0.3.1.dist-info/WHEEL
keccaky-0.3.1.dist-info/RECORD
