Metadata-Version: 2.1
Name: keccaky
Version: 0.3.1
Summary: Secure and easy-to-use keccak
Home-page: https://github.com/olivmath/keccaky.git
License: MIT
Keywords: keccak,ethereum,sha3,hash
Author: Lucas Oliveira
Author-email: olivmath@protonmail.com
Requires-Python: >=3.8,<4.0
Classifier: Development Status :: 5 - Production/Stable
Classifier: Intended Audience :: Developers
Classifier: License :: OSI Approved :: MIT License
Classifier: Operating System :: OS Independent
Classifier: Programming Language :: Python
Classifier: Programming Language :: Python :: 3
Classifier: Programming Language :: Python :: 3.8
Classifier: Programming Language :: Python :: 3.9
Classifier: Programming Language :: Python :: 3.10
Classifier: Programming Language :: Python :: 3.11
Classifier: Programming Language :: Python :: 3.12
Classifier: Topic :: Security :: Cryptography
Classifier: Topic :: Software Development :: Libraries
Classifier: Topic :: Software Development :: Libraries :: Python Modules
Project-URL: Documentation, https://pypi.org/project/keccaky/
Project-URL: Repository, https://github.com/olivmath/keccaky.git
